Workbook
Name salario: 'Simulador'!$B$4
Name aporte: 'Simulador'!$B$5
Name taxa_mensal: 'Simulador'!$B$6
Name anos: 'Simulador'!$B$7
Name perfil: 'Simulador'!$B$8

Sheet Simulador
A1: PLANEJADOR DE INVESTIMENTOS
A3: Dados | D3: Resultado
A4: Salário mensal | B4: 5000 | D4: Patrimônio acumulado | E4: =FV(taxa_mensal,anos*12,-aporte,0,0)
A5: Aporte mensal | B5: =B4*30% | D5: Dividendos por mês | E5: =E4*taxa_mensal
A6: Rendimento mensal | B6: 0.008 | D6: Total investido | E6: =aporte*anos*12
A7: Prazo (anos) | B7: 10 | D7: Rendimento acumulado | E7: =E4-E6
A8: Perfil | B8: Moderado
A11: Projeção
A12: Anos | B12: Patrimônio | C12: Total investido | D12: Rendimento | E12: Dividendos/mês
A13: 2 | B13: =FV(taxa_mensal,A13*12,-aporte,0,0) | C13: =aporte*A13*12 | D13: =B13-C13 | E13: =B13*taxa_mensal
A14: 5 | B14: =FV(taxa_mensal,A14*12,-aporte,0,0) | C14: =aporte*A14*12 | D14: =B14-C14 | E14: =B14*taxa_mensal
A15: 10 | B15: =FV(taxa_mensal,A15*12,-aporte,0,0) | C15: =aporte*A15*12 | D15: =B15-C15 | E15: =B15*taxa_mensal
A16: 20 | B16: =FV(taxa_mensal,A16*12,-aporte,0,0) | C16: =aporte*A16*12 | D16: =B16-C16 | E16: =B16*taxa_mensal
A17: 30 | B17: =FV(taxa_mensal,A17*12,-aporte,0,0) | C17: =aporte*A17*12 | D17: =B17-C17 | E17: =B17*taxa_mensal
A20: Distribuição do aporte
A21: Tipo de FII | B21: % | C21: Valor mensal
A22: Tijolo | B22: =VLOOKUP(perfil&"|"&A22,Apoio!$D$3:$E$20,2,FALSE) | C22: =aporte*B22
A23: Papel | B23: =VLOOKUP(perfil&"|"&A23,Apoio!$D$3:$E$20,2,FALSE) | C23: =aporte*B23
A24: Híbrido | B24: =VLOOKUP(perfil&"|"&A24,Apoio!$D$3:$E$20,2,FALSE) | C24: =aporte*B24
A25: FOF | B25: =VLOOKUP(perfil&"|"&A25,Apoio!$D$3:$E$20,2,FALSE) | C25: =aporte*B25
A26: Desenvolvimento | B26: =VLOOKUP(perfil&"|"&A26,Apoio!$D$3:$E$20,2,FALSE) | C26: =aporte*B26
A27: Agro | B27: =VLOOKUP(perfil&"|"&A27,Apoio!$D$3:$E$20,2,FALSE) | C27: =aporte*B27
A28: Total | B28: =SUM(B22:B27) | C28: =SUM(C22:C27)

Sheet Apoio
A1: Perfis | D1: Chave | E1: %
A2: Perfil | B2: Descrição
A3: Conservador | B3: Maior concentração em fundos de menor volatilidade. | D3: Conservador|Tijolo | E3: 0.3
A4: Moderado | B4: Distribuição equilibrada. | D4: Conservador|Papel | E4: 0.25
A5: Arrojado | B5: Maior exposição a estratégias de crescimento. | D5: Conservador|Híbrido | E5: 0.2
D6: Conservador|FOF | E6: 0.1
D7: Conservador|Desenvolvimento | E7: 0.05
A8: Tipos de FII | D8: Conservador|Agro | E8: 0.1
A9: Tijolo | D9: Moderado|Tijolo | E9: 0.25
A10: Papel | D10: Moderado|Papel | E10: 0.2
A11: Híbrido | D11: Moderado|Híbrido | E11: 0.2
A12: FOF | D12: Moderado|FOF | E12: 0.1
A13: Desenvolvimento | D13: Moderado|Desenvolvimento | E13: 0.1
A14: Agro | D14: Moderado|Agro | E14: 0.15
D15: Arrojado|Tijolo | E15: 0.15
D16: Arrojado|Papel | E16: 0.15
A17: Observação | D17: Arrojado|Híbrido | E17: 0.2
A18: Percentuais usados apenas para a simulação. | D18: Arrojado|FOF | E18: 0.1
D19: Arrojado|Desenvolvimento | E19: 0.2
D20: Arrojado|Agro | E20: 0.2
